simple_task_tracker/__init__.py
simple_task_tracker/main.py
simple_task_tracker/db_migrations/v1.sql
simple_task_tracker/db_migrations/v2.sql
simple_task_tracker-2.5.2.dist-info/LICENSE
simple_task_tracker-2.5.2.dist-info/METADATA
simple_task_tracker-2.5.2.dist-info/WHEEL
simple_task_tracker-2.5.2.dist-info/entry_points.txt
simple_task_tracker-2.5.2.dist-info/top_level.txt
simple_task_tracker-2.5.2.dist-info/RECORD
