Metadata-Version: 2.1
Name: simple-task-tracker
Version: 2.5.2
Summary: Simple Task Tracker CLI
Home-page: https://github.com/ismailbenhallam/simple-task-tracker/
Author: Ismail BENHALLAM
Author-email: ismailben44@gmail.com
Keywords: track,task,time
Classifier: Environment :: Console
Classifier: Programming Language :: Python :: 3.11
Classifier: License :: OSI Approved :: MIT License
Classifier: Operating System :: OS Independent
Requires-Python: >=3.11
License-File: LICENSE
Requires-Dist: typer==0.12.5
